networkpype/__init__.py
networkpype/auth.py
networkpype/factory.py
networkpype/rest/__init__.py
networkpype/rest/connection.py
networkpype/rest/manager.py
networkpype/rest/method.py
networkpype/rest/processor/__init__.py
networkpype/rest/processor/base.py
networkpype/rest/processor/time_synchronizer.py
networkpype/rest/request.py
networkpype/rest/response.py
networkpype/throttler/__init__.py
networkpype/throttler/context.py
networkpype/throttler/rate_limit.py
networkpype/throttler/throttler.py
networkpype/time_synchronizer.py
networkpype/websocket/__init__.py
networkpype/websocket/connection.py
networkpype/websocket/manager.py
networkpype/websocket/processor/__init__.py
networkpype/websocket/processor/base.py
networkpype/websocket/request.py
networkpype/websocket/response.py
networkpype-1.0.1.dist-info/LICENSE
networkpype-1.0.1.dist-info/METADATA
networkpype-1.0.1.dist-info/WHEEL
networkpype-1.0.1.dist-info/RECORD
