Metadata-Version: 2.3
Name: networkpype
Version: 1.0.1
Summary: NetworkPype is a Python library for building efficient network communication pipelines, supporting both REST and WebSocket protocols with built-in rate limiting and time synchronization.
Author: Gianluca Pagliara
Author-email: pagliara.gianluca@gmail.com
Requires-Python: >=3.13,<4.0
Classifier: Programming Language :: Python :: 3
Classifier: Programming Language :: Python :: 3.13
Requires-Dist: aiohttp (>=3.10.0,<4.0.0)
Requires-Dist: aioresponses (>=0.7.8,<0.8.0)
Requires-Dist: numpy (>=2.2.2,<3.0.0)
